nexus/__init__.py
nexus/admin.py
nexus/api.py
nexus/auth.py
nexus/cli.py
nexus/config.py
nexus/core.py
nexus/database.py
nexus/middleware.py
nexus/monitoring.py
nexus/plugins.py
nexus/utils.py
nexus_platform-0.1.5.dist-info/LICENSE
nexus_platform-0.1.5.dist-info/METADATA
nexus_platform-0.1.5.dist-info/WHEEL
nexus_platform-0.1.5.dist-info/entry_points.txt
nexus_platform-0.1.5.dist-info/RECORD
