Metadata-Version: 2.3
Name: nexus-platform
Version: 0.1.5
Summary: The Ultimate Plugin-Based Application Platform - Build modular, scalable applications with ease
License: MIT
Keywords: framework,plugin-system,modular,fastapi,async,microservices,api,rest,websocket,cli,application-platform,enterprise
Author: Nexus Team
Author-email: team@nexus.dev
Maintainer: Nexus Team
Maintainer-email: team@nexus.dev
Requires-Python: >=3.11,<4.0
Classifier: Development Status :: 5 - Production/Stable
Classifier: Environment :: Web Environment
Classifier: Framework :: AsyncIO
Classifier: Framework :: FastAPI
Classifier: Intended Audience :: Developers
Classifier: License :: OSI Approved :: MIT License
Classifier: Operating System :: OS Independent
Classifier: Programming Language :: Python :: 3
Classifier: Programming Language :: Python :: 3.11
Classifier: Programming Language :: Python :: 3.12
Classifier: Programming Language :: Python :: 3.13
Classifier: Topic :: Internet :: WWW/HTTP :: Dynamic Content
Classifier: Topic :: Internet :: WWW/HTTP :: HTTP Servers
Classifier: Topic :: Software Development :: Code Generators
Classifier: Topic :: Software Development :: Libraries :: Application Frameworks
Classifier: Topic :: Software Development :: Libraries :: Python Modules
Classifier: Topic :: System :: Systems Administration
Classifier: Typing :: Typed
Provides-Extra: all-databases
Provides-Extra: email
Provides-Extra: full
Provides-Extra: mariadb
Provides-Extra: messaging
Provides-Extra: mongodb
Provides-Extra: mysql
Provides-Extra: postgresql
Provides-Extra: redis
Provides-Extra: sqlite
Provides-Extra: task-scheduler
Requires-Dist: aiofiles (>=23.2.1,<24.0.0)
Requires-Dist: aiomysql (>=0.2.0,<0.3.0) ; extra == "mysql" or extra == "mariadb" or extra == "all-databases" or extra == "full"
Requires-Dist: aioredis (>=2.0.1,<3.0.0) ; extra == "redis" or extra == "all-databases" or extra == "full"
Requires-Dist: aiosqlite (>=0.19.0,<0.20.0) ; extra == "sqlite" or extra == "all-databases" or extra == "full"
Requires-Dist: apscheduler (>=3.10.4,<4.0.0) ; extra == "task-scheduler" or extra == "full"
Requires-Dist: asyncpg (>=0.29.0,<0.30.0) ; extra == "postgresql" or extra == "all-databases" or extra == "full"
Requires-Dist: click (>=8.1.7,<9.0.0)
Requires-Dist: croniter (>=2.0.1,<3.0.0) ; extra == "task-scheduler" or extra == "full"
Requires-Dist: email-validator (>=2.1.0,<3.0.0)
Requires-Dist: emails (>=0.6,<0.7) ; extra == "email" or extra == "full"
Requires-Dist: fastapi (>=0.109.0,<0.110.0)
Requires-Dist: jinja2 (>=3.1.2,<4.0.0) ; extra == "email" or extra == "full"
Requires-Dist: motor (>=3.3.2,<4.0.0) ; extra == "mongodb" or extra == "all-databases" or extra == "full"
Requires-Dist: passlib[bcrypt] (>=1.7.4,<2.0.0)
Requires-Dist: psutil (>=5.9.0,<6.0.0)
Requires-Dist: psycopg2-binary (>=2.9.9,<3.0.0) ; extra == "postgresql" or extra == "all-databases" or extra == "full"
Requires-Dist: pydantic (>=2.5.3,<3.0.0)
Requires-Dist: pydantic-settings (>=2.1.0,<3.0.0)
Requires-Dist: pymongo (>=4.6.1,<5.0.0) ; extra == "mongodb" or extra == "all-databases" or extra == "full"
Requires-Dist: pymysql (>=1.1.0,<2.0.0) ; extra == "mysql" or extra == "mariadb" or extra == "all-databases" or extra == "full"
Requires-Dist: python-dotenv (>=1.0.0,<2.0.0)
Requires-Dist: python-jose[cryptography] (>=3.3.0,<4.0.0)
Requires-Dist: python-json-logger (>=2.0.7,<3.0.0)
Requires-Dist: python-multipart (>=0.0.6,<0.0.7)
Requires-Dist: python-socketio (>=5.11.0,<6.0.0) ; extra == "messaging" or extra == "full"
Requires-Dist: pyyaml (>=6.0.1,<7.0.0)
Requires-Dist: redis (>=5.0.1,<6.0.0) ; extra == "redis" or extra == "all-databases" or extra == "full"
Requires-Dist: sqlalchemy[asyncio] (>=2.0.25,<3.0.0)
Requires-Dist: toml (>=0.10.2,<0.11.0)
Requires-Dist: uvicorn (>=0.27.0,<0.28.0)
Requires-Dist: websockets (>=12.0,<13.0) ; extra == "messaging" or extra == "full"
Project-URL: Bug Tracker, https://github.com/dnviti/nexus-platform/issues
Project-URL: Changelog, https://github.com/dnviti/nexus-platform/blob/main/CHANGELOG.md
Project-URL: Documentation, https://docs.nexus.dev
Project-URL: Discussions, https://github.com/dnviti/nexus-platform/discussions
Project-URL: Discord, https://discord.gg/nexus
Project-URL: Funding, https://github.com/sponsors/dnviti
Project-URL: Homepage, https://nexus.dev
Project-URL: Repository, https://github.com/dnviti/nexus-platform
Project-URL: Twitter, https://twitter.com/nexus_dev
